limonade/__init__.py
limonade/data.py
limonade/exceptions.py
limonade/histo_utils.py
limonade/loaders.py
limonade/misc.py
limonade/plot.py
limonade/utils.py
limonade-0.9.1.dist-info/LICENCE
limonade-0.9.1.dist-info/METADATA
limonade-0.9.1.dist-info/WHEEL
limonade-0.9.1.dist-info/entry_points.txt
limonade-0.9.1.dist-info/top_level.txt
limonade-0.9.1.dist-info/RECORD
