Metadata-Version: 2.1
Name: limonade
Version: 0.9.1
Summary: List mode native data engine.
Home-page: https://gitlab.com/tehilden/limonade
Author: Timo Hilden
Author-email: timo.hilden@helsinki.fi
Project-URL: Bug Tracker, https://gitlab.com/tehilden/limonade
Classifier: Programming Language :: Python :: 3
Classifier: License :: OSI Approved :: MIT License
Classifier: Operating System :: OS Independent
Classifier: Development Status :: 4 - Beta
Requires-Python: >=3.7
License-File: LICENCE
Requires-Dist: numpy
Requires-Dist: scipy
Requires-Dist: appdirs
